Shift_Register/src/piso.v
//piso shift register
module piso #(
    parameter N = 4
    )(
    input wire clk,
    input wire rst,
    input wire load,
    input wire [N-1:0] parallel_in,
    output wire serial_out
    );

    reg [N-1:0] shift_reg;

    always @(posedge clk) begin
        if (rst) begin
            shift_reg <= {N{1'b0}};
        end
        else if (load) begin
            shift_reg <= parallel_in;
        end
        else begin
            shift_reg <= {1'b0, shift_reg[N-1:1]};
        end
    end
    assign serial_out = shift_reg[0];
endmodule

Shift_Register/tb/tb_piso.v
//testbench for PISO Shift Register
`timescale 1ns / 1ps

module tb_piso;
    parameter N = 4;
    reg clk;
    reg rst;
    reg load;
    reg [N-1:0] parallel_in;
    wire serial_out;

    piso #(.N(N)) dut(
        .clk(clk),
        .rst(rst),
        .load(load),
        .parallel_in(parallel_in),
        .serial_out(serial_out)
    );

    initial clk = 0;
    always #5 clk = ~clk;

    always @(posedge clk) begin
        #1;
        $display("Time: %0t | rst: %b | load: %b | parallel_in: %b | shift_reg: %b | serial_out: %b",
                 $time, rst, load, parallel_in, dut.shift_reg, serial_out);
    end

    initial begin
        $dumpfile("Shift_Register/wave/piso.vcd");
        $dumpvars(0, tb_piso);

        // Initialize
        rst = 1;
        load = 0;
        parallel_in = 0;

        repeat (2) @(negedge clk);
        rst = 0;

        load = 1; parallel_in = 4'b1010; @(negedge clk);

        load = 0;
        repeat (4) @(negedge clk);

        $finish;

    end
endmodule

Sequential Logic & Timing/Shift_Register/wave/piso.vcd
$date
	Sat Dec 27 09:31:38 2025
$end
$version
	Icarus Verilog
$end
$timescale
	1ps
$end
$scope module tb_piso $end
$var wire 1 ! serial_out $end
$var parameter 32 " N $end
$var reg 1 # clk $end
$var reg 1 $ load $end
$var reg 4 % parallel_in [3:0] $end
$var reg 1 & rst $end
$scope module dut $end
$var wire 1 # clk $end
$var wire 1 $ load $end
$var wire 4 ' parallel_in [3:0] $end
$var wire 1 & rst $end
$var wire 1 ! serial_out $end
$var parameter 32 ( N $end
$var reg 4 ) shift_reg [3:0] $end
$upscope $end
$upscope $end
$enddefinitions $end
$comment Show the parameter values. $end
$dumpall
b100 (
b100 "
$end
#0
$dumpvars
bx )
b0 '
1&
b0 %
0$
0#
x!
$end
#5000
0!
b0 )
1#
#10000
0#
#15000
1#
#20000
b1010 %
b1010 '
1$
0&
0#
#25000
b1010 )
1#
#30000
0$
0#
#35000
1!
b101 )
1#
#40000
0#
#45000
0!
b10 )
1#
#50000
0#
#55000
1!
b1 )
1#
#60000
0#
#65000
0!
b0 )
1#
