Sequential Logic & Timing/Up_Down_Counter/src/up_down_counter.v
//up_down_counter

module up_down_counter #(
    parameter N = 4
    )(
        input wire clk,
        input wire rst,
        input wire en,
        input wire up_down,
        output reg [N-1:0] count
    );

    always @(posedge clk) begin
        if (rst) begin
            count = {N{1'b0}};
        end
        else if (en) begin
            if (up_down) begin
                count <= count + 1'b1;
            end
            else begin
                count <= count - 1'b1;
            end
        end
        else begin
            count <= count;
        end
    end
endmodule

Sequential Logic & Timing/Up_Down_Counter/tb/tb_up_down_counter.v
//up_down_counter testbench
`timescale 1ns / 1ps

module tb_up_down_counter;

    parameter N = 4;
    reg clk;
    reg rst; 
    reg en;
    reg up_down;
    wire [N-1:0] count;
    
    up_down_counter #(.N(N)) dut(
        .clk     	(clk      ),
        .rst     	(rst      ),
        .en      	(en       ),
        .up_down 	(up_down  ),
        .count   	(count    )
    );

    initial clk = 0;
    always #5 clk = ~clk;

    always @(posedge clk) begin
            $display("rst=%b , en=%b ,updown=%b",rst,en,up_down);
            $display("count = %b" , count);
        end

    initial begin
        $dumpfile("Up_Down_Counter/wave/up_down_counter.vcd");
        $dumpvars(0,tb_up_down_counter);

        //test
        rst=1; en=0; up_down=1; #5;
        repeat (2) @(posedge clk);
        
        rst=0; en=1; #50; 
        @(posedge clk);

        up_down=0; #50;
        @(posedge clk);

        en=0; #5;
        @(posedge clk);

        $finish;
    end

endmodule

Sequential Logic & Timing/Up_Down_Counter/wave/up_down_counter.vcd
$date
	Wed Dec 24 11:37:25 2025
$end
$version
	Icarus Verilog
$end
$timescale
	1ps
$end
$scope module tb_up_down_counter $end
$var wire 4 ! count [3:0] $end
$var parameter 32 " N $end
$var reg 1 # clk $end
$var reg 1 $ en $end
$var reg 1 % rst $end
$var reg 1 & up_down $end
$scope module dut $end
$var wire 1 # clk $end
$var wire 1 $ en $end
$var wire 1 % rst $end
$var wire 1 & up_down $end
$var parameter 32 ' N $end
$var reg 4 ( count [3:0] $end
$upscope $end
$upscope $end
$enddefinitions $end
$comment Show the parameter values. $end
$dumpall
b100 '
b100 "
$end
#0
$dumpvars
bx (
1&
1%
0$
0#
bx !
$end
#5000
b0 !
b0 (
1#
#10000
0#
#15000
1#
#20000
0#
#25000
1$
0%
1#
#30000
0#
#35000
b1 !
b1 (
1#
#40000
0#
#45000
b10 !
b10 (
1#
#50000
0#
#55000
b11 !
b11 (
1#
#60000
0#
#65000
b100 !
b100 (
1#
#70000
0#
#75000
b11 !
b11 (
0&
1#
#80000
0#
#85000
b10 !
b10 (
1#
#90000
0#
#95000
b1 !
b1 (
1#
#100000
0#
#105000
b0 !
b0 (
1#
#110000
0#
#115000
b1111 !
b1111 (
1#
#120000
0#
#125000
0$
1#
