Mux_case/src/mux_4to1_case.v
// 4:1 mux using case statement
module mux_4to1_case (
    input wire a,
    input wire b,
    input wire c,
    input wire d,
    input wire [1:0] selection,
    output reg y
);

    always @(*) begin
        case (selection)
            2'b00: y = a;
            2'b01: y = b;
            2'b10: y = c;
            2'b11: y = d;
            default: y = 1'b0;

        endcase
    end

endmodule

RTL Fundamentals/Mux_case/tb/tb_mux_4to1.v
`timescale 1ns/1ps

module mux_4to1_case_tb;
    reg a;
    reg b;
    reg c;
    reg d;
    reg [1:0] selection;
    wire y;

    mux_4to1_case dut(
        .a         	(a          ),
        .b         	(b          ),
        .c         	(c          ),
        .d         	(d          ),
        .selection 	(selection  ),
        .y         	(y          )
    );

    initial begin

        $dumpfile("wave/mux_4to1.vcd");
        $dumpvars(0, mux_4to1_case_tb);

        // Test case 1
        $display("Test case 1: 0000");

        a=0;b=0;c=0;d=0;

        selection = 2'b00; #10;
        $display("selection=%b => y=%b", selection, y);
        selection = 2'b01; #10;
        $display("selection=%b => y=%b", selection, y);
        selection = 2'b10; #10;
        $display("selection=%b => y=%b", selection, y);
        selection = 2'b11; #10;
        $display("selection=%b => y=%b", selection, y);

        // Test case 2
        $display("Test case 2: 0101");

        a=0;b=1;c=0;d=1;

        selection = 2'b00; #10;
        $display("selection=%b => y=%b", selection, y);
        selection = 2'b01; #10;
        $display("selection=%b => y=%b", selection, y);
        selection = 2'b10; #10;
        $display("selection=%b => y=%b", selection, y);
        selection = 2'b11; #10;
        $display("selection=%b => y=%b", selection, y);

        $finish;
    end

endmodule

RTL Fundamentals/Mux_case/wave/mux_4to1.vcd
$date
	Tue Dec 23 20:15:57 2025
$end
$version
	Icarus Verilog
$end
$timescale
	1ps
$end
$scope module mux_4to1_case_tb $end
$var wire 1 ! y $end
$var reg 1 " a $end
$var reg 1 # b $end
$var reg 1 $ c $end
$var reg 1 % d $end
$var reg 2 & selection [1:0] $end
$scope module dut $end
$var wire 1 " a $end
$var wire 1 # b $end
$var wire 1 $ c $end
$var wire 1 % d $end
$var wire 2 ' selection [1:0] $end
$var reg 1 ! y $end
$upscope $end
$upscope $end
$enddefinitions $end
$comment Show the parameter values. $end
$dumpall
$end
#0
$dumpvars
b0 '
b0 &
0%
0$
0#
0"
0!
$end
#10000
b1 &
b1 '
#20000
b10 &
b10 '
#30000
b11 &
b11 '
#40000
b0 &
b0 '
1%
1#
#50000
1!
b1 &
b1 '
#60000
0!
b10 &
b10 '
#70000
1!
b11 &
b11 '
