Shift_Counter/src/johnson_counter.v
//johnson counter

module johnson_counter #(
    parameter N = 4
)(
    input wire clk,
    input wire rst,
    output reg [N-1:0] count
);

always @(posedge clk) begin
    if (rst) begin
        count <= {(N){1'b0}};
    end
    else begin
        count = {~count[0], count[N-1:1]};
    end
end
endmodule

Shift_Counter/tb/tb_johnson_counter.v
//testbench johnson counter
`timescale 1ns / 1ps

module tb_johnson_counter;
    parameter N=4;
    reg clk;
    reg rst;
    wire [N-1:0] count;
    
    johnson_counter #(
        .N 	(N ))
    dut(
        .clk   	(clk    ),
        .rst   	(rst    ),
        .count 	(count  )
    );

    initial clk = 0;
    always #5 clk = ~clk;

    always @(posedge clk) begin
        #1;
        $display("Time: %0t | rst: %b === count: %b",
                 $time, rst, count);
    end

    initial begin
        $dumpfile("Shift_Counter/wave/johnson_counter.vcd");
        $dumpvars(0, tb_johnson_counter);

        // Initialize
        rst=1;
        repeat (2) @(negedge clk);
        rst=0;
        repeat (20) @(negedge clk);

        $finish();
    end

endmodule

Shift_Counter/wave/johnson_counter.vcd
$date
	Sat Dec 27 10:13:31 2025
$end
$version
	Icarus Verilog
$end
$timescale
	1ps
$end
$scope module tb_johnson_counter $end
$var wire 4 ! count [3:0] $end
$var parameter 32 " N $end
$var reg 1 # clk $end
$var reg 1 $ rst $end
$scope module dut $end
$var wire 1 # clk $end
$var wire 1 $ rst $end
$var parameter 32 % N $end
$var reg 4 & count [3:0] $end
$upscope $end
$upscope $end
$enddefinitions $end
$comment Show the parameter values. $end
$dumpall
b100 %
b100 "
$end
#0
$dumpvars
bx &
1$
0#
bx !
$end
#5000
b0 !
b0 &
1#
#10000
0#
#15000
1#
#20000
0$
0#
#25000
b1000 !
b1000 &
1#
#30000
0#
#35000
b1100 !
b1100 &
1#
#40000
0#
#45000
b1110 !
b1110 &
1#
#50000
0#
#55000
b1111 !
b1111 &
1#
#60000
0#
#65000
b111 !
b111 &
1#
#70000
0#
#75000
b11 !
b11 &
1#
#80000
0#
#85000
b1 !
b1 &
1#
#90000
0#
#95000
b0 !
b0 &
1#
#100000
0#
#105000
b1000 !
b1000 &
1#
#110000
0#
#115000
b1100 !
b1100 &
1#
#120000
0#
#125000
b1110 !
b1110 &
1#
#130000
0#
#135000
b1111 !
b1111 &
1#
#140000
0#
#145000
b111 !
b111 &
1#
#150000
0#
#155000
b11 !
b11 &
1#
#160000
0#
#165000
b1 !
b1 &
1#
#170000
0#
#175000
b0 !
b0 &
1#
#180000
0#
#185000
b1000 !
b1000 &
1#
#190000
0#
#195000
b1100 !
b1100 &
1#
#200000
0#
#205000
b1110 !
b1110 &
1#
#210000
0#
#215000
b1111 !
b1111 &
1#
