Sequential Logic & Timing/Shift_Counter/src/ring_counter.v
//ring counter

module ring_counter #(
    parameter N = 4
)(
    input wire clk,
    input wire rst,
    output reg [N-1:0] count
);

always @(posedge clk) begin
    if (rst) begin
        count <= {{(N-1){1'b0}},1'b1};
    end
    else begin
        count = {count[0], count[N-1:1]};
    end
end
endmodule

Sequential Logic & Timing/Shift_Counter/tb/tb_ring_counter.v
//testbench ring counter
`timescale 1ns / 1ps

module tb_ring_counter;
    parameter N=4;
    reg clk;
    reg rst;
    wire [N-1:0] count;
    
    ring_counter #(
        .N 	(N ))
    dut(
        .clk   	(clk    ),
        .rst   	(rst    ),
        .count 	(count  )
    );

    initial clk = 0;
    always #5 clk = ~clk;

    always @(posedge clk) begin
        #1;
        $display("Time: %0t | rst: %b === count: %b",
                 $time, rst, count);
    end

    initial begin
        $dumpfile("Shift_Counter/wave/ring_counter.vcd");
        $dumpvars(0, tb_ring_counter);

        // Initialize
        rst=1;
        repeat (2) @(negedge clk);
        rst=0;
        repeat (20) @(negedge clk);

        $finish();
    end

endmodule

Shift_Counter/wave/ring_counter.vcd
$date
	Sat Dec 27 09:54:13 2025
$end
$version
	Icarus Verilog
$end
$timescale
	1ps
$end
$scope module tb_ring_counter $end
$var wire 4 ! count [3:0] $end
$var parameter 32 " N $end
$var reg 1 # clk $end
$var reg 1 $ rst $end
$scope module dut $end
$var wire 1 # clk $end
$var wire 1 $ rst $end
$var parameter 32 % N $end
$var reg 4 & count [3:0] $end
$upscope $end
$upscope $end
$enddefinitions $end
$comment Show the parameter values. $end
$dumpall
b100 %
b100 "
$end
#0
$dumpvars
bx &
1$
0#
bx !
$end
#5000
b1 !
b1 &
1#
#10000
0#
#15000
1#
#20000
0$
0#
#25000
b1000 !
b1000 &
1#
#30000
0#
#35000
b100 !
b100 &
1#
#40000
0#
#45000
b10 !
b10 &
1#
#50000
0#
#55000
b1 !
b1 &
1#
#60000
0#
#65000
b1000 !
b1000 &
1#
#70000
0#
#75000
b100 !
b100 &
1#
#80000
0#
#85000
b10 !
b10 &
1#
#90000
0#
#95000
b1 !
b1 &
1#
#100000
0#
#105000
b1000 !
b1000 &
1#
#110000
0#
#115000
b100 !
b100 &
1#
#120000
0#
#125000
b10 !
b10 &
1#
#130000
0#
#135000
b1 !
b1 &
1#
#140000
0#
#145000
b1000 !
b1000 &
1#
#150000
0#
#155000
b100 !
b100 &
1#
#160000
0#
#165000
b10 !
b10 &
1#
#170000
0#
#175000
b1 !
b1 &
1#
#180000
0#
#185000
b1000 !
b1000 &
1#
#190000
0#
#195000
b100 !
b100 &
1#
#200000
0#
#205000
b10 !
b10 &
1#
#210000
0#
#215000
b1 !
b1 &
1#
