Sequential Logic & Timing/Clock_Divider/src/clock_divider.v
//clock divider

module clock_divider #(
    parameter N = 4
)(
    input wire clk_in,
    input wire rst,
    output reg clk_out

);

    integer count;
    
    always @(posedge clk_in) begin

        if (rst) begin
            count <= 0;
            clk_out <= 0;
        end
        else begin
            if (count == ((N/2)-1)) begin
                count <= 0;
                clk_out = ~clk_out;
            end
            else begin
                count <= count + 1;
            end
        end
    end
endmodule

Sequential Logic & Timing/Clock_Divider/tb/tb_clock_divider.v
//testbench

`timescale 1ns/1ps

module tb_clock_divider;

parameter N = 4;

reg clk_in;
reg rst;
wire clk_out;


clock_divider #(
    .N 	(N))
dut(
    .clk_in  	(clk_in   ),
    .rst     	(rst      ),
    .clk_out 	(clk_out  )
);

initial clk_in = 0;
always #10 clk_in = ~clk_in;

always @(posedge clk_in) begin
    $display("clk=%b | rst=%b === clk_out=%b", clk_in, rst,clk_out);
end

initial begin
    $dumpfile("Clock_Divider/wave/clock_divider.vcd");
    $dumpvars(0,tb_clock_divider );

    rst = 1; 
    #20
    repeat(2) @(posedge clk_in);

    rst = 0;

    #200
    @(posedge clk_in);

    $finish;
end
endmodule

Sequential Logic & Timing/Clock_Divider/wave/clock_divider.vcd
$date
	Wed Dec 24 14:25:18 2025
$end
$version
	Icarus Verilog
$end
$timescale
	1ps
$end
$scope module tb_clock_divider $end
$var wire 1 ! clk_out $end
$var parameter 32 " N $end
$var reg 1 # clk_in $end
$var reg 1 $ rst $end
$scope module dut $end
$var wire 1 # clk_in $end
$var wire 1 $ rst $end
$var parameter 32 % N $end
$var reg 1 ! clk_out $end
$var integer 32 & count [31:0] $end
$upscope $end
$upscope $end
$enddefinitions $end
$comment Show the parameter values. $end
$dumpall
b100 %
b100 "
$end
#0
$dumpvars
bx &
1$
0#
x!
$end
#10000
0!
b0 &
1#
#20000
0#
#30000
b1 &
0$
1#
#40000
0#
#50000
b0 &
1!
1#
#60000
0#
#70000
b1 &
1#
#80000
0#
#90000
b0 &
0!
1#
#100000
0#
#110000
b1 &
1#
#120000
0#
#130000
b0 &
1!
1#
#140000
0#
#150000
b1 &
1#
#160000
0#
#170000
b0 &
0!
1#
#180000
0#
#190000
b1 &
1#
#200000
0#
#210000
b0 &
1!
1#
#220000
0#
#230000
b1 &
1#
