RTL Fundamentals/Mux_case/src/mux_2to1_case.v
// 2:1 mux using case statement
module mux_2to1_case (
    input wire a,
    input wire b,
    input wire selection,
    output reg y
);

    always @(*) begin
        case (selection)
            1'b0: y = a;
            1'b1: y = b;
            default: y = 1'b0;

        endcase
    end

endmodule

Mux_case/tb/tb_mux_2to1.v
`timescale 1ns/1ps

module mux_2to1_case_tb;
    reg a;
    reg b;
    reg selection;
    wire y;
    
    mux_2to1_case dut(
        .a         	(a          ),
        .b         	(b          ),
        .selection 	(selection  ),
        .y         	(y          )
    );

    initial begin
        $dumpfile("wave/mux_2to1.vcd");
        $dumpvars(0, mux_2to1_case_tb);

        // Test case 1
        $display("Test case 1: selection = 0");
        a = 0; b= 0; selection = 0; #10;
        $display("00: a=%b, b=%b, selection=%b => y=%b", a, b, selection, y);
        a = 0; b= 1; selection = 0; #10;
        $display("01: a=%b, b=%b, selection=%b => y=%b", a, b, selection, y);
        a = 1; b= 0; selection = 0; #10;
        $display("10: a=%b, b=%b, selection=%b => y=%b", a, b, selection, y);
        a = 1; b= 1; selection = 0; #10;
        $display("11: a=%b, b=%b, selection=%b => y=%b", a, b, selection, y);

        // Test case 2
        $display("Test case 2: selection = 1");
        a = 0; b= 0; selection = 1; #10;
        $display("00: a=%b, b=%b, selection=%b => y=%b", a, b, selection, y);
        a = 0; b= 1; selection = 1; #10;
        $display("01: a=%b, b=%b, selection=%b => y=%b", a, b, selection, y);
        a = 1; b= 0; selection = 1; #10;
        $display("10: a=%b, b=%b, selection=%b => y=%b", a, b, selection, y);
        a = 1; b= 1; selection = 1; #10;
        $display("11: a=%b, b=%b, selection=%b => y=%b", a, b, selection, y);

        $finish;
    end


endmodule

Mux_case/wave/mux_2to1.vcd
$date
	Tue Dec 23 20:14:14 2025
$end
$version
	Icarus Verilog
$end
$timescale
	1ps
$end
$scope module mux_2to1_case_tb $end
$var wire 1 ! y $end
$var reg 1 " a $end
$var reg 1 # b $end
$var reg 1 $ selection $end
$scope module dut $end
$var wire 1 " a $end
$var wire 1 # b $end
$var wire 1 $ selection $end
$var reg 1 ! y $end
$upscope $end
$upscope $end
$enddefinitions $end
$comment Show the parameter values. $end
$dumpall
$end
#0
$dumpvars
0$
0#
0"
0!
$end
#10000
1#
#20000
1!
0#
1"
#30000
1#
#40000
0!
1$
0#
0"
#50000
1!
1#
#60000
0!
0#
1"
#70000
1!
1#
