RTL Fundamentals/BinarytoGray/src/bin_to_gray_4bit.v
// binary to gray code converter (4-bit)
module bin_to_gray_4bit (
    input wire [3:0] bin,
    output reg[3:0] gray
);

    always @(*) begin
        gray[3] = bin[3];
        gray[2] = bin[3] ^ bin[2];
        gray[1] = bin[2] ^ bin[1];
        gray[0] = bin[1] ^ bin[0];
    end

endmodule

BinarytoGray/tb/tb_bin_to_gray_4bit.v
//testbench

`timescale 1ns / 1ps
module tb_bin_to_gray_4bit;

    reg [3:0] bin;
    wire [3:0] gray;
    
    bin_to_gray_4bit dut(
        .bin  	(bin   ),
        .gray 	(gray  )
    );

    initial begin
        $dumpfile("wave/bin_to_gray_4bit.vcd");
        $dumpvars(0, tb_bin_to_gray_4bit);

        //test
        $display("Binary to Gray 4-bit");
        bin = 4'b0000; #10;
        $display("%b = %b" , bin , gray);
        bin = 4'b0001; #10;
        $display("%b = %b" , bin , gray);
        bin = 4'b0010; #10;
        $display("%b = %b" , bin , gray);
        bin = 4'b0011; #10;
        $display("%b = %b" , bin , gray);
        bin = 4'b0100; #10;
        $display("%b = %b" , bin , gray);
        bin = 4'b0101; #10;
        $display("%b = %b" , bin , gray);
        bin = 4'b0110; #10;
        $display("%b = %b" , bin , gray);
        bin = 4'b0111; #10;
        $display("%b = %b" , bin , gray);
        bin = 4'b1000; #10;
        $display("%b = %b" , bin , gray);
        bin = 4'b1001; #10;
        $display("%b = %b" , bin , gray);
        bin = 4'b1010; #10;
        $display("%b = %b" , bin , gray);
        bin = 4'b1011; #10;
        $display("%b = %b" , bin , gray);
        bin = 4'b1100; #10;
        $display("%b = %b" , bin , gray);
        bin = 4'b1101; #10;
        $display("%b = %b" , bin , gray);
        bin = 4'b1110; #10;
        $display("%b = %b" , bin , gray);
        bin = 4'b1111; #10;
        $display("%b = %b" , bin , gray);

        $finish;
    end
    
endmodule

BinarytoGray/wave/bin_to_gray_4bit.vcd
$date
	Wed Dec 24 07:44:11 2025
$end
$version
	Icarus Verilog
$end
$timescale
	1ps
$end
$scope module tb_bin_to_gray_4bit $end
$var wire 4 ! gray [3:0] $end
$var reg 4 " bin [3:0] $end
$scope module dut $end
$var wire 4 # bin [3:0] $end
$var reg 4 $ gray [3:0] $end
$upscope $end
$upscope $end
$enddefinitions $end
$comment Show the parameter values. $end
$dumpall
$end
#0
$dumpvars
b0 $
b0 #
b0 "
b0 !
$end
#10000
b1 !
b1 $
b1 "
b1 #
#20000
b11 !
b11 $
b10 "
b10 #
#30000
b10 !
b10 $
b11 "
b11 #
#40000
b110 !
b110 $
b100 "
b100 #
#50000
b111 !
b111 $
b101 "
b101 #
#60000
b101 !
b101 $
b110 "
b110 #
#70000
b100 !
b100 $
b111 "
b111 #
#80000
b1100 !
b1100 $
b1000 "
b1000 #
#90000
b1101 !
b1101 $
b1001 "
b1001 #
#100000
b1111 !
b1111 $
b1010 "
b1010 #
#110000
b1110 !
b1110 $
b1011 "
b1011 #
#120000
b1010 !
b1010 $
b1100 "
b1100 #
#130000
b1011 !
b1011 $
b1101 "
b1101 #
#140000
b1001 !
b1001 $
b1110 "
b1110 #
#150000
b1000 !
b1000 $
b1111 "
b1111 #
