Sequential Logic & Timing/Shift_Register/src/sipo.v
//sipo shift register
module sipo #(
    parameter N = 4
    )(
    input wire clk,
    input wire rst,
    input wire serial_in,
    output reg [N-1:0] parallel_out
    );

    always @(posedge clk) begin
        if (rst) begin
            parallel_out <= {N{1'b0}};
        end
        else begin
            parallel_out <= {parallel_out[N-2:0], serial_in};
        end
    end

endmodule

Shift_Register/tb/tb_sipo.v
//testbench for SIPO Shift Register
`timescale 1ns / 1ps

module tb_sipo;
    parameter N = 4;
    reg clk;
    reg rst;
    reg serial_in;
    wire [N-1:0] parallel_out;

    sipo #(.N(N)) dut(
        .clk(clk),
        .rst(rst),
        .serial_in(serial_in),
        .parallel_out(parallel_out)
    );

    initial clk = 0;
    always #5 clk = ~clk;

    always @(posedge clk) begin
        #1;
        $display("Time: %0t | rst: %b | serial_in: %b | parallel_out: %b",
                 $time, rst, serial_in, parallel_out);
    end

    initial begin
        $dumpfile("Shift_Register/wave/sipo.vcd");
        $dumpvars(0, tb_sipo);

        // Initialize
        rst = 1;
        serial_in = 0;

        // Avoid race with DUT sampling on posedge: drive inputs on negedge.
        repeat (2) @(negedge clk);
        rst = 0;

        @(negedge clk); serial_in = 1;
        @(negedge clk); serial_in = 0;
        @(negedge clk); serial_in = 1;
        @(negedge clk); serial_in = 0;

        repeat (N + 2) @(negedge clk);

        $finish;

    end
endmodule

Shift_Register/wave/sipo.vcd
$date
	Sat Dec 27 08:09:05 2025
$end
$version
	Icarus Verilog
$end
$timescale
	1ps
$end
$scope module tb_sipo $end
$var wire 4 ! parallel_out [3:0] $end
$var parameter 32 " N $end
$var reg 1 # clk $end
$var reg 1 $ rst $end
$var reg 1 % serial_in $end
$scope module dut $end
$var wire 1 # clk $end
$var wire 1 $ rst $end
$var wire 1 % serial_in $end
$var parameter 32 & N $end
$var reg 4 ' parallel_out [3:0] $end
$upscope $end
$upscope $end
$enddefinitions $end
$comment Show the parameter values. $end
$dumpall
b100 &
b100 "
$end
#0
$dumpvars
bx '
0%
1$
0#
bx !
$end
#5000
b0 !
b0 '
1#
#10000
0#
#15000
1#
#20000
0$
0#
#25000
1#
#30000
1%
0#
#35000
b1 !
b1 '
1#
#40000
0%
0#
#45000
b10 !
b10 '
1#
#50000
1%
0#
#55000
b101 !
b101 '
1#
#60000
0%
0#
#65000
b1010 !
b1010 '
1#
#70000
0#
#75000
b100 !
b100 '
1#
#80000
0#
#85000
b1000 !
b1000 '
1#
#90000
0#
#95000
b0 !
b0 '
1#
