Sequential Logic & Timing/Shift_Register/src/siso.v
//siso shift register
module siso #(
    parameter N = 4
    )(
    input wire clk,
    input wire rst,
    input wire serial_in,
    output wire serial_out
    );

    reg [N-1:0] shift_reg;

    always @(posedge clk) begin
        if (rst) begin
            shift_reg <= {N{1'b0}};
        end
        else begin
            shift_reg <= {serial_in, shift_reg[N-1:1]};
        end
    end

    assign serial_out = shift_reg[0];
endmodule

Sequential Logic & Timing/Shift_Register/tb/tb_siso.v
//testbench for SISO Shift Register
`timescale 1ns / 1ps

module tb_siso;
    parameter N = 4;
    reg clk;
    reg rst;
    reg serial_in;
    wire serial_out;

    siso #(.N(N)) dut(
        .clk(clk),
        .rst(rst),
        .serial_in(serial_in),
        .serial_out(serial_out)
    );

    initial clk = 0;
    always #5 clk = ~clk;

    always @(posedge clk) begin
        #1;
        $display("Time: %0t | rst: %b | serial_in: %b | shift_reg: %b | serial_out: %b",
                 $time, rst, serial_in, dut.shift_reg, serial_out);
    end

    initial begin
        $dumpfile("Shift_Register/wave/siso.vcd");
        $dumpvars(0, tb_siso);

        // Initialize
        rst = 1;
        serial_in = 0;

        repeat (2) @(negedge clk);
        rst = 0;

        serial_in = 1; @(negedge clk);
        serial_in = 0; @(negedge clk);
        serial_in = 1; @(negedge clk);
        serial_in = 0; @(negedge clk);

        repeat (N + 2) @(negedge clk);

        $finish;

    end
endmodule

Shift_Register/wave/siso.vcd
$date
	Wed Dec 24 21:37:16 2025
$end
$version
	Icarus Verilog
$end
$timescale
	1ps
$end
$scope module tb_siso $end
$var wire 1 ! serial_out $end
$var parameter 32 " N $end
$var reg 1 # clk $end
$var reg 1 $ rst $end
$var reg 1 % serial_in $end
$scope module dut $end
$var wire 1 # clk $end
$var wire 1 $ rst $end
$var wire 1 % serial_in $end
$var wire 1 ! serial_out $end
$var parameter 32 & N $end
$var reg 4 ' shift_reg [3:0] $end
$upscope $end
$upscope $end
$enddefinitions $end
$comment Show the parameter values. $end
$dumpall
b100 &
b100 "
$end
#0
$dumpvars
bx '
0%
1$
0#
x!
$end
#5000
0!
b0 '
1#
#10000
0#
#15000
1#
#20000
1%
0$
0#
#25000
b1000 '
1#
#30000
0%
0#
#35000
b100 '
1#
#40000
1%
0#
#45000
b1010 '
1#
#50000
0%
0#
#55000
1!
b101 '
1#
#60000
0#
#65000
0!
b10 '
1#
#70000
0#
#75000
1!
b1 '
1#
#80000
0#
#85000
0!
b0 '
1#
