Register_File/src/reg_file.v
//register file

module reg_file #(
    parameter DATA_WIDTH = 8,
    parameter ADDR_WIDTH = 4,
    parameter DEPTH = 1 << ADDR_WIDTH
)(
    input wire clk,
    input wire rst,
    input wire we,
    input wire [ADDR_WIDTH-1:0] read_addr1,
    input wire [ADDR_WIDTH-1:0] read_addr2,
    input wire [ADDR_WIDTH-1:0] write_addr,
    input wire [DATA_WIDTH-1:0] write_data,
    output wire [DATA_WIDTH-1:0] read_data1,
    output wire [DATA_WIDTH-1:0] read_data2
);

    // Register array
    reg [DATA_WIDTH-1:0] reg_array [0:DEPTH-1];
    integer i;

    always @(posedge clk) begin
        if (rst) begin
            for (i = 0; i < DEPTH; i = i + 1)
                reg_array[i] <= {DATA_WIDTH{1'b0}};
        end
        else if (we) begin
            reg_array[write_addr] <= write_data;
        end
    end

    assign read_data1 = reg_array[read_addr1];
    assign read_data2 = reg_array[read_addr2];
    
endmodule

Register_File/tb/tb_reg_file.v
`timescale 1ns/1ps

module tb_reg_file;

    parameter DATA_WIDTH = 8;
    parameter ADDR_WIDTH = 3;
    parameter DEPTH = 1 << ADDR_WIDTH;


    reg clk;
    reg rst;
    reg we;
    reg [ADDR_WIDTH-1:0] read_addr1;
    reg [ADDR_WIDTH-1:0] read_addr2;
    reg [ADDR_WIDTH-1:0] write_addr;
    reg [DATA_WIDTH-1:0] write_data;
    wire [DATA_WIDTH-1:0] read_data1;
    wire [DATA_WIDTH-1:0] read_data2;
    
    reg_file #(
        .DATA_WIDTH 	(DATA_WIDTH          ),
        .ADDR_WIDTH 	(ADDR_WIDTH           ),
        .DEPTH      	(DEPTH   ))
    dut(
        .clk        	(clk         ),
        .rst        	(rst         ),
        .we         	(we          ),
        .read_addr1 	(read_addr1  ),
        .read_addr2 	(read_addr2  ),
        .write_addr 	(write_addr  ),
        .write_data 	(write_data  ),
        .read_data1 	(read_data1  ),
        .read_data2 	(read_data2  )
    );
    

    initial clk = 0;
    always #5 clk = ~clk;

    always @(posedge clk) begin
        #1;
        $display("Time: %0t | rst: %b | we: %b | waddr: %h | wdata: %h | raddr1: %h | rdata1: %h | raddr2: %h | rdata2: %h",
                 $time, rst, we, write_addr, write_data, read_addr1, read_data1, read_addr2, read_data2);
    end

    initial begin
        $dumpfile("Register_File/wave/reg_file.vcd");
        $dumpvars(0, tb_reg_file);

        // Initialize
        rst = 1; we = 0; write_addr = 0; write_data = 0; read_addr1 = 0; read_addr2 = 0;

        // Release reset
        @(negedge clk);
        rst = 0;

        // Write data to register 3
        @(negedge clk);
        we = 1; write_addr = 3; write_data = 8'hAA;

        // Write data to register 5
        @(negedge clk);
        we = 1; write_addr = 5; write_data = 8'h55;
        // Disable write
        @(negedge clk);
        we = 0;

        // Read from register 3 and 5
        @(negedge clk);
        read_addr1 = 3; read_addr2 = 5;

        // Read from register 0 and 1
        @(negedge clk);
        read_addr1 = 0; read_addr2 = 1;
        // Finish simulation
        @(negedge clk);
        $finish;
    end

endmodule

Register_File/wave/reg_file.vcd
$date
	Sat Dec 27 12:04:01 2025
$end
$version
	Icarus Verilog
$end
$timescale
	1ps
$end
$scope module tb_reg_file $end
$var wire 8 ! read_data2 [7:0] $end
$var wire 8 " read_data1 [7:0] $end
$var parameter 32 # ADDR_WIDTH $end
$var parameter 32 $ DATA_WIDTH $end
$var parameter 35 % DEPTH $end
$var reg 1 & clk $end
$var reg 3 ' read_addr1 [2:0] $end
$var reg 3 ( read_addr2 [2:0] $end
$var reg 1 ) rst $end
$var reg 1 * we $end
$var reg 3 + write_addr [2:0] $end
$var reg 8 , write_data [7:0] $end
$scope module dut $end
$var wire 1 & clk $end
$var wire 3 - read_addr1 [2:0] $end
$var wire 3 . read_addr2 [2:0] $end
$var wire 8 / read_data1 [7:0] $end
$var wire 8 0 read_data2 [7:0] $end
$var wire 1 ) rst $end
$var wire 1 * we $end
$var wire 3 1 write_addr [2:0] $end
$var wire 8 2 write_data [7:0] $end
$var parameter 32 3 ADDR_WIDTH $end
$var parameter 32 4 DATA_WIDTH $end
$var parameter 35 5 DEPTH $end
$var integer 32 6 i [31:0] $end
$upscope $end
$upscope $end
$enddefinitions $end
$comment Show the parameter values. $end
$dumpall
b1000 5
b1000 4
b11 3
b1000 %
b1000 $
b11 #
$end
#0
$dumpvars
bx 6
b0 2
b0 1
bx 0
bx /
b0 .
b0 -
b0 ,
b0 +
0*
1)
b0 (
b0 '
0&
bx "
bx !
$end
#5000
b0 "
b0 /
b0 !
b0 0
b1000 6
1&
#10000
0)
0&
#15000
1&
#20000
b10101010 ,
b10101010 2
b11 +
b11 1
1*
0&
#25000
1&
#30000
b1010101 ,
b1010101 2
b101 +
b101 1
0&
#35000
1&
#40000
0*
0&
#45000
1&
#50000
b1010101 !
b1010101 0
b101 (
b101 .
b10101010 "
b10101010 /
b11 '
b11 -
0&
#55000
1&
#60000
b0 !
b0 0
b1 (
b1 .
b0 "
b0 /
b0 '
b0 -
0&
